mini_calculator/__init__.py
mini_calculator/calculator.py
minicalculator-0.1.0.post1.dist-info/METADATA
minicalculator-0.1.0.post1.dist-info/WHEEL
minicalculator-0.1.0.post1.dist-info/top_level.txt
minicalculator-0.1.0.post1.dist-info/RECORD
