Metadata-Version: 2.1
Name: minicalculator
Version: 0.1.0.post1
Summary: A basic Calculator
Home-page: https://github.com/Idris01/calculator
Author: Idris Adebowale
Author-email: idrys01@gmail.com
License: MIT
Platform: UNKNOWN
Classifier: License :: OSI Approved :: MIT License
Classifier: Programming Language :: Python :: 3
Classifier: Programming Language :: Python :: 3.8
